{
  "refreshLabel": "Refresh snapshot",
  "sections": [
    {
      "type": "metrics",
      "title": "Activity",
      "items": [
        { "label": "Open items", "binding": "draftSnapshot.openItems" },
        { "label": "At risk", "binding": "draftSnapshot.atRisk" }
      ]
    },
    {
      "type": "list",
      "title": "Highlights",
      "binding": "draftSnapshot.highlights",
      "emptyLabel": "No highlights yet."
    },
    { "type": "text", "title": "Summary", "binding": "draftSnapshot.summary" }
  ]
}
